sample_py_package/__init__.py
sample_py_package/cities.json
sample_py_package/states_info.py
generated_demo_repo-0.0.0.dist-info/METADATA
generated_demo_repo-0.0.0.dist-info/WHEEL
generated_demo_repo-0.0.0.dist-info/top_level.txt
generated_demo_repo-0.0.0.dist-info/RECORD
