Metadata-Version: 2.1
Name: generated-demo-repo
Version: 0.0.0
Summary: Demo for Python Packaging
Author-email: Amit Vikram Raj <avr13405@gmail.com>
License: MIT
Keywords: python,bash,makefile,pypi,ci-cd,setuptools,wheels,package-development,github-actions,pypi-package,pre-commit-hooks,pyproject-toml,gitactions-workflow,github-actions-enabled,pre-commit-ci,pre-commit-config
Classifier: Programming Language :: Python :: 3
Requires-Python: >=3.7
Requires-Dist: numpy
Requires-Dist: importlib-metadata ; python_version >= "3.8"
Provides-Extra: dev
Requires-Dist: generated-demo-repo[release,static-code-qa,test] ; extra == 'dev'
Provides-Extra: release
Requires-Dist: build ; extra == 'release'
Requires-Dist: twine ; extra == 'release'
Provides-Extra: static-code-qa
Requires-Dist: pre-commit ; extra == 'static-code-qa'
Provides-Extra: test
Requires-Dist: pytest ; extra == 'test'
Requires-Dist: pytest-cov ; extra == 'test'
